LICENSE
echo1_coco_preview/__init__.py
echo1_coco_preview/echo1_coco_preview.py
echo1_coco_preview-0.1.1.dist-info/entry_points.txt
echo1_coco_preview-0.1.1.dist-info/LICENSE
echo1_coco_preview-0.1.1.dist-info/WHEEL
echo1_coco_preview-0.1.1.dist-info/METADATA
echo1_coco_preview-0.1.1.dist-info/RECORD
